{
    "example_source": [
        "x我还",
        "澄清",
        "了",
        "在该",
        "会议上",
        "提出的",
        "若干",
        "事项",
        "。"
    ],
    "example_target": [
        "<s>",
        "xi",
        "xwas",
        "xable",
        "xto",
        "xprovide",
        "xclarification",
        "xon",
        "xsome",
        "xof",
        "xthe",
        "xmatters",
        "xwhich",
        "xwere",
        "xraised",
        "xat",
        "xthat",
        "xmeeting",
        ".",
        "</s>"
    ],
    "hypotheses": [
        {
            "hypothesis": [
                "xi",
                "xalso",
                "xclarified",
                "xa",
                "xnumber",
                "xof",
                "xmatters",
                "xraised",
                "xby",
                "xthe",
                "xmeeting",
                "."
            ],
            "score": -10.469483375549316
        },
        {
            "hypothesis": [
                "xi",
                "xalso",
                "xdiscussed",
                "xa",
                "xnumber",
                "xof",
                "xmatters",
                "xraised",
                "xby",
                "xthe",
                "xmeeting",
                "."
            ],
            "score": -10.74081039428711
        },
        {
            "hypothesis": [
                "xi",
                "xalso",
                "xclarified",
                "xa",
                "xnumber",
                "xof",
                "xmatters",
                "xraised",
                "."
            ],
            "score": -10.888883590698242
        },
        {
            "hypothesis": [
                "xi",
                "xalso",
                "xclarified",
                "xa",
                "xnumber",
                "xof",
                "xmatters",
                "xraised",
                "xby",
                "xthe",
                "xconference",
                "."
            ],
            "score": -11.324610710144043
        },
        {
            "hypothesis": [
                "xi",
                "xalso",
                "xsaw",
                "xa",
                "xnumber",
                "xof",
                "xmatters",
                "xraised",
                "xby",
                "xthe",
                "xmeeting",
                "."
            ],
            "score": -11.377498626708984
        },
        {
            "hypothesis": [
                "xi",
                "xalso",
                "xdiscussed",
                "xa",
                "xnumber",
                "xof",
                "xmatters",
                "xraised",
                "xby",
                "xthe",
                "xconference",
                "."
            ],
            "score": -11.568180084228516
        },
        {
            "hypothesis": [
                "xi",
                "xalso",
                "xclarified",
                "xa",
                "xnumber",
                "xof",
                "xissues",
                "xraised",
                "xby",
                "xthe",
                "xmeeting",
                "."
            ],
            "score": -11.572039604187012
        },
        {
            "hypothesis": [
                "xi",
                "xalso",
                "xdiscussed",
                "xthe",
                "xnumber",
                "xof",
                "xmatters",
                "xraised",
                "xby",
                "xthe",
                "xmeeting",
                "."
            ],
            "score": -11.591883659362793
        },
        {
            "hypothesis": [
                "xi",
                "xalso",
                "xalso",
                "xclarified",
                "xa",
                "xnumber",
                "xof",
                "xmatters",
                "xraised",
                "xby",
                "xthe",
                "xmeeting",
                "."
            ],
            "score": -12.419189453125
        },
        {
            "hypothesis": [
                "xi",
                "xalso",
                "xclarified",
                "xa",
                "xnumber",
                "xof",
                "xmatters",
                "xraised",
                "xby",
                "xa",
                "xnumber",
                "xof",
                "xmatters",
                "."
            ],
            "score": -13.296003341674805
        }
    ],
    "diagnostic_info": "eyJ0IjogIjIwMjQtMDctMTVUMDc6MDI6NTguMTM0MjU5IiwgImgiOiAiQ1lKIiwgInUiOiAiQWRtaW5pc3RyYXRvciJ9"
}