{
    "example_source": [
        "x我还",
        "澄清",
        "了",
        "在该",
        "会议上",
        "提出的",
        "若干",
        "事项",
        "。"
    ],
    "example_target": [
        "<s>",
        "xi",
        "xwas",
        "xable",
        "xto",
        "xprovide",
        "xclarification",
        "xon",
        "xsome",
        "xof",
        "xthe",
        "xmatters",
        "xwhich",
        "xwere",
        "xraised",
        "xat",
        "xthat",
        "xmeeting",
        ".",
        "</s>"
    ],
    "hypotheses": [
        {
            "hypothesis": [
                "xi",
                "xalso",
                "xclarify",
                "xa",
                "xnumber",
                "xof",
                "xmatters",
                "xthat",
                "xhave",
                "xbeen",
                "xraised",
                "xat",
                "xthe",
                "xmeeting",
                "."
            ],
            "score": -8.385967254638672
        },
        {
            "hypothesis": [
                "xi",
                "xwould",
                "xalso",
                "xlike",
                "xto",
                "xclarify",
                "xa",
                "xnumber",
                "xof",
                "xmatters",
                "xraised",
                "xat",
                "xthe",
                "xmeeting",
                "."
            ],
            "score": -8.773972511291504
        },
        {
            "hypothesis": [
                "xi",
                "xalso",
                "xclarify",
                "xa",
                "xnumber",
                "xof",
                "xmatters",
                "xthat",
                "xhave",
                "xbeen",
                "xraised",
                "xby",
                "xthe",
                "xconference",
                "."
            ],
            "score": -8.89570426940918
        },
        {
            "hypothesis": [
                "xi",
                "xwould",
                "xalso",
                "xlike",
                "xto",
                "xclarify",
                "xa",
                "xnumber",
                "xof",
                "xmatters",
                "xraised",
                "xby",
                "xthe",
                "xconference",
                "."
            ],
            "score": -8.985782623291016
        },
        {
            "hypothesis": [
                "xi",
                "xalso",
                "xclarify",
                "xa",
                "xnumber",
                "xof",
                "xmatters",
                "xthat",
                "xhave",
                "xbeen",
                "xraised",
                "xby",
                "xthe",
                "xmeeting",
                "."
            ],
            "score": -9.255792617797852
        },
        {
            "hypothesis": [
                "xi",
                "xalso",
                "xclarify",
                "xa",
                "xnumber",
                "xof",
                "xmatters",
                "xthat",
                "xhave",
                "xbeen",
                "xput",
                "xin",
                "xplace",
                "xat",
                "xthe",
                "xmeeting",
                "."
            ],
            "score": -9.393817901611328
        },
        {
            "hypothesis": [
                "xi",
                "xwould",
                "xalso",
                "xlike",
                "xto",
                "xclarify",
                "xa",
                "xnumber",
                "xof",
                "xmatters",
                "xraised",
                "xby",
                "xthe",
                "xmeeting",
                "."
            ],
            "score": -9.610377311706543
        },
        {
            "hypothesis": [
                "xi",
                "xwould",
                "xalso",
                "xlike",
                "xto",
                "xclarify",
                "xa",
                "xnumber",
                "xof",
                "xmatters",
                "xthat",
                "xhave",
                "xbeen",
                "xraised",
                "xat",
                "xthe",
                "xmeeting",
                "."
            ],
            "score": -10.16480541229248
        },
        {
            "hypothesis": [
                "xi",
                "xwould",
                "xalso",
                "xlike",
                "xto",
                "xclarify",
                "xa",
                "xnumber",
                "xof",
                "xmatters",
                "xthat",
                "xhave",
                "xbeen",
                "xraised",
                "xby",
                "xthe",
                "xconference",
                "."
            ],
            "score": -10.360595703125
        },
        {
            "hypothesis": [
                "xi",
                "xwould",
                "xalso",
                "xlike",
                "xto",
                "xclarify",
                "xa",
                "xnumber",
                "xof",
                "xmatters",
                "xthat",
                "xhave",
                "xbeen",
                "xput",
                "xin",
                "xplace",
                "xat",
                "xthe",
                "xmeeting",
                "."
            ],
            "score": -11.219959259033203
        }
    ],
    "diagnostic_info": "eyJ0IjogIjIwMjQtMDctMTVUMDc6MzQ6NDcuMjIxNDYxIiwgImgiOiAiQ1lKIiwgInUiOiAiQWRtaW5pc3RyYXRvciJ9"
}